<samba:parameter name="admin users"
                 context="S"
				 type="list"
                 xmlns:samba="http://www.samba.org/samba/DTD/samba-doc">
<description>
    <para> このパラメーターは、共有上で管理者権限が与えられるユーザーのリストである。
    指定されたユーザーは、すべてのファイル操作をスーパーユーザー (root) として実行できる。</para>

    <para> このリストに登録されているユーザーは、
    ファイルのパーミッションに関係なくあらゆる操作を行うことができてしまうため、
    このオプションは十分に注意して使用すべきである。</para>

    <para>このパラメーターは、 Samba 3.0 における <smbconfoption
    name="security">share</smbconfoption> 環境では動作しない。
    これは仕様である。</para>
</description>
<value type="default"/>
<value type="example">jason</value>
</samba:parameter>
