<samba:parameter name="tls certfile"
                 type="string"
                 context="G"
		 xmlns:samba="http://www.samba.org/samba/DTD/samba-doc">
 <description>
	 <para>このオプションは、RSA 証明書を含む(PEM 形式の)ファイルを
	 設定することができる。 </para>
	 <para>このパスが、 /. から始まっていない場合、
	 <smbconfoption name="private dir"/>からの相対パスとなる。</para>
 </description>

 <related>tls keyfile</related>
 <related>tls crlfile</related>
 <related>tls dh params file</related>
 <related>tls enabled</related>
 <related>tls cafile</related>
 <value type="default">tls/cert.pem</value>
</samba:parameter>
